sensemore/SMWiredPy.py
sensemore/__init__.py
sensemore/example.py
SMWiredPy-1.0.4.dist-info/LICENSE
SMWiredPy-1.0.4.dist-info/METADATA
SMWiredPy-1.0.4.dist-info/WHEEL
SMWiredPy-1.0.4.dist-info/top_level.txt
SMWiredPy-1.0.4.dist-info/RECORD
