Metadata-Version: 2.1
Name: SMWiredPy
Version: 1.0.4
Summary: Sensemore Wired Python Interface
Home-page: https://www.sensemore.io
Author: sensemore
Author-email: hello@sensemore.io
License: MIT
Project-URL: Bug Reports, https://github.com/sensemore/SMWiredPy/issues
Project-URL: Source, https://github.com/sensemore/SMWiredPy
Keywords: SMCom,sensemore,wired accelerometer,accelerometer sensor,python accelerometer sensor
Platform: UNKNOWN
Requires-Python: >=3.6
License-File: LICENSE
Requires-Dist: pyserial (==3.5)
Requires-Dist: pybind11 (==2.7.0)
Requires-Dist: SMComPy
